jq.cp312-win_amd64.pyd
jq-1.11.0.dist-info/licenses/LICENSE
jq-1.11.0.dist-info/METADATA
jq-1.11.0.dist-info/WHEEL
jq-1.11.0.dist-info/top_level.txt
jq-1.11.0.dist-info/RECORD
